nanolsap/__init__.py
nanolsap/_lsap.pyd
nanolsap/_lsap.pyi
nanolsap/_version.py
nanolsap/py.typed
nanolsap-0.1.4.dist-info/LICENSE
nanolsap-0.1.4.dist-info/METADATA
nanolsap-0.1.4.dist-info/WHEEL
nanolsap-0.1.4.dist-info/top_level.txt
nanolsap-0.1.4.dist-info/RECORD
