Metadata-Version: 2.1
Name: nanolsap
Version: 0.1.4
Summary: Python module to solve the linear sum assignment problem (LSAP) low memory friendly
Author-email: hzqmwne <huangzhengqmwne@sina.cn>
License: BSD-3-Clause
Project-URL: Homepage, https://github.com/hzqmwne/nanolsap
Keywords: lsap,munkres,kuhn-munkres,linear sum assignment problem
Classifier: License :: OSI Approved :: BSD License
Classifier: Programming Language :: Python :: 3
Classifier: Programming Language :: Python :: 3.9
Requires-Python: >=3.9
License-File: LICENSE
Requires-Dist: numpy >=1.21.0
